eristropy/__init__.py
eristropy/bootstrap.py
eristropy/difference.py
eristropy/extras.py
eristropy/gp.py
eristropy/linreg.py
eristropy/sample_entropy.py
eristropy/stationarity.py
eristropy/utils.py
eristropy/validation.py
eristropy-0.1.0.dist-info/LICENSE.md
eristropy-0.1.0.dist-info/METADATA
eristropy-0.1.0.dist-info/WHEEL
eristropy-0.1.0.dist-info/RECORD
