Metadata-Version: 2.1
Name: eristropy
Version: 0.1.0
Summary: EristroPy: End-to-end entropy analysis of time series signals
Home-page: https://zblanks.github.io/eristropy
License: MIT
Keywords: entropy,time-series,optimization
Author: Zachary Blanks
Author-email: zdb6dz@virginia.edu
Requires-Python: >=3.9,<3.12
Classifier: Development Status :: 3 - Alpha
Classifier: License :: OSI Approved :: MIT License
Classifier: Operating System :: OS Independent
Classifier: Programming Language :: Python :: 3
Classifier: Programming Language :: Python :: 3.9
Classifier: Programming Language :: Python :: 3.10
Classifier: Programming Language :: Python :: 3.11
Requires-Dist: numba (>=0.57.1,<0.58.0)
Requires-Dist: numpy (>=1.24,<2.0)
Requires-Dist: optuna (>=3.2.0,<4.0.0)
Requires-Dist: pandas (>=2.0.3,<3.0.0)
Requires-Dist: scikit-learn (>=1.3.0,<2.0.0)
Requires-Dist: scipy (>=1.11.1,<2.0.0)
Requires-Dist: statsmodels (>=0.14.0,<0.15.0)
Requires-Dist: tqdm (>=4.65.0,<5.0.0)
Project-URL: Repository, https://github.com/zblanks/eristropy
